{
  "main": {
    "id": "80a5bb0434892748",
    "type": "split",
    "children": [
      {
        "id": "ea241486258e9d5c",
        "type": "tabs",
        "children": [
          {
            "id": "4884316bb249fab5",
            "type": "leaf",
            "state": {
              "type": "markdown",
              "state": {
                "file": "README.md",
                "mode": "source",
                "source": false
              }
            }
          }
        ]
      }
    ],
    "direction": "vertical"
  },
  "left": {
    "id": "8f5cba81f1977cca",
    "type": "split",
    "children": [
      {
        "id": "c63ac633a7812c45",
        "type": "tabs",
        "children": [
          {
            "id": "a7ec7eb1cf195444",
            "type": "leaf",
            "state": {
              "type": "file-explorer",
              "state": {
                "sortOrder": "alphabetical"
              }
            }
          },
          {
            "id": "9595369d3647cabc",
            "type": "leaf",
            "state": {
              "type": "search",
              "state": {
                "query": "",
                "matchingCase": false,
                "explainSearch": false,
                "collapseAll": false,
                "extraContext": false,
                "sortOrder": "alphabetical"
              }
            }
          },
          {
            "id": "2164f63b743fda80",
            "type": "leaf",
            "state": {
              "type": "bookmarks",
              "state": {}
            }
          }
        ]
      }
    ],
    "direction": "horizontal",
    "width": 300
  },
  "right": {
    "id": "ddbcbc23e309cb76",
    "type": "split",
    "children": [
      {
        "id": "97801b1659aaa161",
        "type": "tabs",
        "children": [
          {
            "id": "2f69bdc9f83a0a7b",
            "type": "leaf",
            "state": {
              "type": "backlink",
              "state": {
                "file": "README.md",
                "collapseAll": false,
                "extraContext": false,
                "sortOrder": "alphabetical",
                "showSearch": false,
                "searchQuery": "",
                "backlinkCollapsed": false,
                "unlinkedCollapsed": true
              }
            }
          },
          {
            "id": "f8a5501a9d2e5aa5",
            "type": "leaf",
            "state": {
              "type": "outgoing-link",
              "state": {
                "file": "README.md",
                "linksCollapsed": false,
                "unlinkedCollapsed": true
              }
            }
          },
          {
            "id": "8667a37e543928e0",
            "type": "leaf",
            "state": {
              "type": "tag",
              "state": {
                "sortOrder": "frequency",
                "useHierarchy": true
              }
            }
          },
          {
            "id": "bece511129bfa889",
            "type": "leaf",
            "state": {
              "type": "outline",
              "state": {
                "file": "README.md"
              }
            }
          }
        ]
      }
    ],
    "direction": "horizontal",
    "width": 300,
    "collapsed": true
  },
  "left-ribbon": {
    "hiddenItems": {
      "switcher:Open quick switcher": false,
      "graph:Open graph view": false,
      "canvas:Create new canvas": false,
      "daily-notes:Open today's daily note": false,
      "templates:Insert template": false,
      "command-palette:Open command palette": false
    }
  },
  "active": "4884316bb249fab5",
  "lastOpenFiles": [
    "docs/Frame 1 (1).png.import",
    "docs/Frame 1 (1).png",
    "docs/type-hints.png.import",
    "docs/type-hints.png",
    "docs/local_path.png.import",
    "local_path.png.import",
    "docs/local_path.png",
    "docs/localpath.png",
    "local_path.png",
    "docs/external_editor.png.import",
    "docs/external_editor.png",
    "Untitled.md",
    "docs",
    "README.md"
  ]
}